abupy/__init__.py
abupy/AlphaBu/ABuAlpha.py
abupy/AlphaBu/ABuPickBase.py
abupy/AlphaBu/ABuPickStockExecute.py
abupy/AlphaBu/ABuPickStockMaster.py
abupy/AlphaBu/ABuPickStockWorker.py
abupy/AlphaBu/ABuPickTimeExecute.py
abupy/AlphaBu/ABuPickTimeMaster.py
abupy/AlphaBu/ABuPickTimeWorker.py
abupy/AlphaBu/__init__.py
abupy/BetaBu/ABuAtrPosition.py
abupy/BetaBu/ABuBeta.py
abupy/BetaBu/ABuKellyPosition.py
abupy/BetaBu/ABuPositionBase.py
abupy/BetaBu/ABuPtPosition.py
abupy/BetaBu/__init__.py
abupy/CheckBu/ABuChecker.py
abupy/CheckBu/ABuChecks.py
abupy/CheckBu/ABuFuncUtil.py
abupy/CheckBu/ABuProcessor.py
abupy/CheckBu/__init__.py
abupy/CoreBu/ABu.py
abupy/CoreBu/ABuBase.py
abupy/CoreBu/ABuDeprecated.py
abupy/CoreBu/ABuEnv.py
abupy/CoreBu/ABuEnvProcess.py
abupy/CoreBu/ABuFixes.py
abupy/CoreBu/ABuParallel.py
abupy/CoreBu/ABuPdHelper.py
abupy/CoreBu/ABuStore.py
abupy/CoreBu/__init__.py
abupy/CrawlBu/ABuXqApi.py
abupy/CrawlBu/ABuXqConsts.py
abupy/CrawlBu/ABuXqCrawl.py
abupy/CrawlBu/ABuXqCrawlImp.py
abupy/CrawlBu/ABuXqFile.py
abupy/CrawlBu/__init__.py
abupy/DLBu/ABuDL.py
abupy/DLBu/ABuDLImgStd.py
abupy/DLBu/ABuDLTVSplit.py
abupy/DLBu/__init__.py
abupy/ExtBu/__init__.py
abupy/ExtBu/funcsigs.py
abupy/ExtBu/odict.py
abupy/ExtBu/six.py
abupy/ExtBu/empyrical/__init__.py
abupy/ExtBu/empyrical/_version.py
abupy/ExtBu/empyrical/stats.py
abupy/ExtBu/empyrical/utils.py
abupy/ExtBu/futures/__init__.py
abupy/ExtBu/futures/_base.py
abupy/ExtBu/futures/process.py
abupy/ExtBu/futures/thread.py
abupy/ExtBu/joblib/__init__.py
abupy/ExtBu/joblib/_compat.py
abupy/ExtBu/joblib/_memory_helpers.py
abupy/ExtBu/joblib/_multiprocessing_helpers.py
abupy/ExtBu/joblib/_parallel_backends.py
abupy/ExtBu/joblib/disk.py
abupy/ExtBu/joblib/format_stack.py
abupy/ExtBu/joblib/func_inspect.py
abupy/ExtBu/joblib/hashing.py
abupy/ExtBu/joblib/logger.py
abupy/ExtBu/joblib/memory.py
abupy/ExtBu/joblib/my_exceptions.py
abupy/ExtBu/joblib/numpy_pickle.py
abupy-0.4.0.dist-info/DESCRIPTION.rst
abupy-0.4.0.dist-info/METADATA
abupy-0.4.0.dist-info/RECORD
abupy-0.4.0.dist-info/WHEEL
abupy-0.4.0.dist-info/metadata.json
abupy-0.4.0.dist-info/top_level.txt
