Metadata-Version: 2.0
Name: abupy
Version: 0.4.0
Summary: 阿布量化系统
Home-page: http://abuquant.com/
Author: 阿布
Author-email: service@abuquant.com
License: GPL
Download-URL: https://github.com/bbfamily/abu
Keywords: 阿布,abu,quant,quantization,crawler,spider,scrapy,stock,machine learning,股票,机器学习,量化,爬虫
Platform: any
Requires-Dist: matplotlib
Requires-Dist: numpy
Requires-Dist: pandas
Requires-Dist: requests
Requires-Dist: scikit-learn
Requires-Dist: scipy
Requires-Dist: seaborn
Requires-Dist: statsmodels
